tests/__init__.py
tests/test_toolrouter.py
toolrouter/__init__.py
toolrouter/client.py
toolrouter-0.2.0.dist-info/licenses/LICENSE
toolrouter-0.2.0.dist-info/METADATA
toolrouter-0.2.0.dist-info/WHEEL
toolrouter-0.2.0.dist-info/top_level.txt
toolrouter-0.2.0.dist-info/RECORD
