Metadata-Version: 2.4
Name: toolrouter
Version: 0.2.0
Summary: Python client for the ToolRouter API
Home-page: https://toolrouter.ai
Author: ToolRouter
Author-email: admin@toolrouter.ai
Project-URL: Bug Tracker, https://github.com/Toolrouter-Inc/toolrouter-python-sdk/issues
Project-URL: Documentation, https://docs.toolrouter.ai
Classifier: Programming Language :: Python :: 3
Classifier: Programming Language :: Python :: 3.6
Classifier: Programming Language :: Python :: 3.7
Classifier: Programming Language :: Python :: 3.8
Classifier: Programming Language :: Python :: 3.9
Classifier: Programming Language :: Python :: 3.10
Classifier: License :: OSI Approved :: Apache Software License
Classifier: Operating System :: OS Independent
Classifier: Intended Audience :: Developers
Classifier: Topic :: Software Development :: Libraries :: Python Modules
Requires-Python: >=3.6
License-File: LICENSE
Requires-Dist: httpx>=0.24.0
Requires-Dist: pydantic>=2.0.0
Requires-Dist: typing-extensions>=4.0.0
Provides-Extra: dev
Requires-Dist: pytest>=6.0.0; extra == "dev"
Requires-Dist: black>=21.5b2; extra == "dev"
Requires-Dist: isort>=5.9.1; extra == "dev"
Requires-Dist: flake8>=3.9.2; extra == "dev"
Requires-Dist: twine>=3.4.1; extra == "dev"
Requires-Dist: build>=0.7.0; extra == "dev"
Dynamic: author
Dynamic: author-email
Dynamic: classifier
Dynamic: description
Dynamic: description-content-type
Dynamic: home-page
Dynamic: license-file
Dynamic: project-url
Dynamic: provides-extra
Dynamic: requires-dist
Dynamic: requires-python
Dynamic: summary
